odoo/addons/mrp_mto_owner/README.rst
odoo/addons/mrp_mto_owner/__init__.py
odoo/addons/mrp_mto_owner/__manifest__.py
odoo/addons/mrp_mto_owner/i18n/it.po
odoo/addons/mrp_mto_owner/i18n/mrp_mto_owner.pot
odoo/addons/mrp_mto_owner/models/__init__.py
odoo/addons/mrp_mto_owner/models/stock_rule.py
odoo/addons/mrp_mto_owner/readme/DESCRIPTION.rst
odoo/addons/mrp_mto_owner/static/description/icon.png
odoo/addons/mrp_mto_owner/static/description/index.html
odoo/addons/mrp_mto_owner/tests/__init__.py
odoo/addons/mrp_mto_owner/tests/test_mrp_mto_owner.py
odoo_addon_mrp_mto_owner-16.0.1.0.0.4.dist-info/METADATA
odoo_addon_mrp_mto_owner-16.0.1.0.0.4.dist-info/WHEEL
odoo_addon_mrp_mto_owner-16.0.1.0.0.4.dist-info/top_level.txt
odoo_addon_mrp_mto_owner-16.0.1.0.0.4.dist-info/RECORD
